nbgradio/__init__.py
nbgradio/builder.py
nbgradio/cli.py
nbgradio/deployer.py
nbgradio/parser.py
nbgradio/renderer.py
nbgradio/version.txt
nbgradio-0.0.3.dist-info/METADATA
nbgradio-0.0.3.dist-info/WHEEL
nbgradio-0.0.3.dist-info/entry_points.txt
nbgradio-0.0.3.dist-info/licenses/LICENSE
nbgradio-0.0.3.dist-info/RECORD
