Metadata-Version: 2.4
Name: nbgradio
Version: 0.0.3
Summary: Convert Jupyter notebooks to static HTML websites with live Gradio apps
Project-URL: homepage, https://github.com/gradio-app/nbgradio
Project-URL: repository, https://github.com/gradio-app/nbgradio
Author-email: Abubakar Abid <abubakar@hf.co>
License-File: LICENSE
Classifier: License :: OSI Approved :: MIT License
Classifier: Operating System :: OS Independent
Classifier: Programming Language :: Python :: 3
Requires-Python: >3.9
Requires-Dist: click>=8.0.0
Requires-Dist: fastapi>=0.100.0
Requires-Dist: gradio>=5.0.0
Requires-Dist: huggingface-hub>=0.20.0
Requires-Dist: mistune>=3.0.0
Requires-Dist: nbformat>=5.0.0
Requires-Dist: pygments>=2.15.0
Requires-Dist: toml>=0.10.0
Requires-Dist: uvicorn>=0.20.0
Provides-Extra: dev
Requires-Dist: pytest; extra == 'dev'
Requires-Dist: ruff==0.9.3; extra == 'dev'
